CHANGELOG.txt
LICENCE.txt
MANIFEST.in
README.txt
setup.py
mycalculator/__init__.py
mycalculator/base.py
mycalculator.egg-info/PKG-INFO
mycalculator.egg-info/SOURCES.txt
mycalculator.egg-info/dependency_links.txt
mycalculator.egg-info/top_level.txt