Metadata-Version: 1.1
Name: mycalculator
Version: 0.0.1
Summary: A very basic calculator
Home-page: UNKNOWN
Author: Vishal Patil
Author-email: vishalbpatil1@gmail.com
License: MIT
Keywords: calculator
Platform: UNKNOWN
Classifier: License :: OSI Approved :: MIT License
Classifier: Programming Language :: Python :: 3
Classifier: Programming Language :: Python :: 3.7
